mercadopago/__init__.py
mercadopago/sdk.py
mercadopago/config/__init__.py
mercadopago/config/config.py
mercadopago/config/request_options.py
mercadopago/core/__init__.py
mercadopago/core/mp_base.py
mercadopago/http/__init__.py
mercadopago/http/http_client.py
mercadopago/resources/__init__.py
mercadopago/resources/advanced_payment.py
mercadopago/resources/card.py
mercadopago/resources/card_token.py
mercadopago/resources/chargeback.py
mercadopago/resources/customer.py
mercadopago/resources/disbursement_refund.py
mercadopago/resources/identification_type.py
mercadopago/resources/merchant_order.py
mercadopago/resources/payment.py
mercadopago/resources/payment_methods.py
mercadopago/resources/plan.py
mercadopago/resources/preapproval.py
mercadopago/resources/preference.py
mercadopago/resources/refund.py
mercadopago/resources/subscription.py
mercadopago/resources/user.py
mercadopago-2.2.3.dist-info/LICENSE
mercadopago-2.2.3.dist-info/METADATA
mercadopago-2.2.3.dist-info/WHEEL
mercadopago-2.2.3.dist-info/top_level.txt
mercadopago-2.2.3.dist-info/RECORD
