Metadata-Version: 2.1
Name: mercadopago
Version: 2.2.3
Summary: Mercadopago SDK module for Payments integration
Author-email: Mercado Pago <mp_sdk@mercadopago.com>
License: MIT License
Project-URL: Homepage, https://mercadopago.com
Project-URL: Repository, https://github.com/mercadopago/sdk-python
Keywords: api,mercadopago,checkout,payment in sdk integration,lts
Classifier: License :: OSI Approved :: MIT License
Classifier: Operating System :: OS Independent
Classifier: Topic :: Software Development :: Libraries :: Python Modules
Classifier: Programming Language :: Python :: 3
Classifier: Programming Language :: Python :: 3.4
Classifier: Programming Language :: Python :: 3.5
Classifier: Programming Language :: Python :: 3.6
Classifier: Programming Language :: Python :: 3.7
Classifier: Programming Language :: Python :: 3.8
Classifier: Programming Language :: Python :: 3.9
Classifier: Programming Language :: Python :: 3.10
Classifier: Programming Language :: Python :: 3.11
Requires-Python: >=3.7
License-File: LICENSE
Requires-Dist: requests
Provides-Extra: testing
Requires-Dist: unittest; extra == "testing"
